iknowpy.libs/libiknowengine-1970f643.so
iknowpy.libs/libiknowmodelrux-4d65296c.so
iknowpy.libs/libiknowmodelja-a64db207.so
iknowpy.libs/libiknowmodelsv-8ea402f3.so
iknowpy.libs/libiknowmodelukx-c1c6c11b.so
iknowpy.libs/libiknowmodelptx-a186157f.so
iknowpy.libs/libiknowmodelpt-2a809cd3.so
iknowpy.libs/libicuuc-8d3ee996.so.74.2
iknowpy.libs/libiknowmodelcom-86d16949.so
iknowpy.libs/libiknowmodeles-0485eb95.so
iknowpy.libs/libiknowmodeldex-6641205a.so
iknowpy.libs/libiknowmodelnlx-15cb4507.so
iknowpy.libs/libiknowmodelde-cdf277b8.so
iknowpy.libs/libiknowmodelru-6da32938.so
iknowpy.libs/libicudata-04d94cde.so.74.2
iknowpy.libs/libiknowmodelcs-949dfe29.so
iknowpy.libs/libiknowmodelfr-621240ad.so
iknowpy.libs/libiknowmodelen-7b7ff93c.so
iknowpy.libs/libiknowmodelenx-de3faba8.so
iknowpy.libs/libicui18n-ab99e81c.so.74.2
iknowpy.libs/libiknowmodelfrx-263f5be2.so
iknowpy.libs/libiknowmodelsvx-675ed1df.so
iknowpy.libs/libiknowmodelesx-daf4f0b2.so
iknowpy.libs/libiknowshell-fe647076.so
iknowpy.libs/libiknowmodelcsx-e6f5b144.so
iknowpy.libs/libicuio-76449b92.so.74.2
iknowpy.libs/libiknowmodeluk-f6c8c07c.so
iknowpy.libs/libiknowcore-addae648.so
iknowpy.libs/libiknowbase-695a55d5.so
iknowpy.libs/libiknowali-23e1d5b2.so
iknowpy.libs/libiknowmodeljax-dd7c09c4.so
iknowpy.libs/libiknowmodelnl-74192a35.so
iknowpy-1.5.4.dist-info/LICENSE_ICU
iknowpy-1.5.4.dist-info/LICENSE
iknowpy-1.5.4.dist-info/WHEEL
iknowpy-1.5.4.dist-info/top_level.txt
iknowpy-1.5.4.dist-info/LICENSE_JSON
iknowpy-1.5.4.dist-info/METADATA
iknowpy-1.5.4.dist-info/RECORD
iknowpy/version.py
iknowpy/engine.cpython-313-x86_64-linux-gnu.so
iknowpy/git_revision
iknowpy/engine.cpython-38-x86_64-linux-gnu.so
iknowpy/engine.cpython-311-x86_64-linux-gnu.so
iknowpy/labels.py
iknowpy/__init__.py
iknowpy/engine.cpython-39-x86_64-linux-gnu.so
iknowpy/engine.cpython-312-x86_64-linux-gnu.so
iknowpy/engine.cpython-310-x86_64-linux-gnu.so
