Metadata-Version: 2.1
Name: iknowpy
Version: 1.5.4
Summary: iKnow Natural Language Processing engine
Home-page: https://github.com/intersystems/iknow
Author: InterSystems Corporation
License: MIT
Project-URL: Source, https://github.com/intersystems/iknow
Project-URL: Tracker, https://github.com/intersystems/iknow/issues
Project-URL: Wiki, https://github.com/intersystems/iknow/wiki
Keywords: NLP
Classifier: Development Status :: 5 - Production/Stable
Classifier: License :: OSI Approved :: MIT License
Classifier: Topic :: Scientific/Engineering :: Information Analysis
Classifier: Programming Language :: C++
Classifier: Programming Language :: Cython
Classifier: Programming Language :: Python :: 3
Classifier: Programming Language :: Python :: 3 :: Only
Classifier: Programming Language :: Python :: 3.8
Classifier: Programming Language :: Python :: 3.9
Classifier: Programming Language :: Python :: 3.10
Classifier: Programming Language :: Python :: 3.11
Classifier: Programming Language :: Python :: 3.12
Classifier: Programming Language :: Python :: 3.13
Classifier: Programming Language :: Python :: Implementation :: CPython
Classifier: Operating System :: MacOS :: MacOS X
Classifier: Operating System :: Microsoft :: Windows
Classifier: Operating System :: POSIX
Requires-Python: >=3.8
License-File: LICENSE
License-File: LICENSE_ICU
License-File: LICENSE_JSON
